{
  "main": {
    "id": "f7c8f5577fa1ef91",
    "type": "split",
    "children": [
      {
        "id": "b377c52786ff0eb1",
        "type": "tabs",
        "children": [
          {
            "id": "af6d23556121e701",
            "type": "leaf",
            "state": {
              "type": "markdown",
              "state": {
                "file": "杂记/啤酒江湖的醉意.md",
                "mode": "source",
                "source": false
              }
            }
          }
        ]
      }
    ],
    "direction": "vertical"
  },
  "left": {
    "id": "a041910abdb8498e",
    "type": "split",
    "children": [
      {
        "id": "127e137628388ca5",
        "type": "tabs",
        "children": [
          {
            "id": "43681b39462fd6e9",
            "type": "leaf",
            "state": {
              "type": "file-explorer",
              "state": {
                "sortOrder": "alphabetical"
              }
            }
          },
          {
            "id": "f9853bd8eb07b164",
            "type": "leaf",
            "state": {
              "type": "search",
              "state": {
                "query": "",
                "matchingCase": false,
                "explainSearch": false,
                "collapseAll": false,
                "extraContext": false,
                "sortOrder": "alphabetical"
              }
            }
          },
          {
            "id": "335271137982f1f2",
            "type": "leaf",
            "state": {
              "type": "bookmarks",
              "state": {}
            }
          }
        ]
      }
    ],
    "direction": "horizontal",
    "width": 307.5
  },
  "right": {
    "id": "60cd4afab2d5469d",
    "type": "split",
    "children": [
      {
        "id": "51a616bb53188398",
        "type": "tabs",
        "children": [
          {
            "id": "9a519ca6be58cc1d",
            "type": "leaf",
            "state": {
              "type": "backlink",
              "state": {
                "file": "杂记/啤酒江湖的醉意.md",
                "collapseAll": true,
                "extraContext": true,
                "sortOrder": "alphabetical",
                "showSearch": false,
                "searchQuery": "",
                "backlinkCollapsed": false,
                "unlinkedCollapsed": true
              }
            }
          },
          {
            "id": "08dda351d2ffaeca",
            "type": "leaf",
            "state": {
              "type": "outgoing-link",
              "state": {
                "file": "杂记/啤酒江湖的醉意.md",
                "linksCollapsed": false,
                "unlinkedCollapsed": true
              }
            }
          },
          {
            "id": "072c0c882a9b5520",
            "type": "leaf",
            "state": {
              "type": "tag",
              "state": {
                "sortOrder": "frequency",
                "useHierarchy": true
              }
            }
          },
          {
            "id": "2f37b1bb749fc4be",
            "type": "leaf",
            "state": {
              "type": "outline",
              "state": {
                "file": "杂记/啤酒江湖的醉意.md"
              }
            }
          },
          {
            "id": "afa1f9c64052e925",
            "type": "leaf",
            "state": {
              "type": "quiet-outline",
              "state": {}
            }
          }
        ],
        "currentTab": 3
      }
    ],
    "direction": "horizontal",
    "width": 300
  },
  "left-ribbon": {
    "hiddenItems": {
      "switcher:打开快速切换": false,
      "graph:查看关系图谱": false,
      "canvas:新建白板": false,
      "daily-notes:打开/创建今天的日记": false,
      "templates:插入模板": false,
      "command-palette:打开命令面板": false,
      "templater-obsidian:Templater": false,
      "obsidian-kanban:创建新看板": false,
      "hidden-folder-obsidian:显示文件夹": false
    }
  },
  "active": "af6d23556121e701",
  "lastOpenFiles": [
    "后端/mysql/binlog.md",
    "2024-05-30.md",
    "前端/第二篇.md",
    "后端/mysql/binlog/binlog-20240603173730442.webp",
    "后端/mysql/binlog",
    "后端/mysql",
    "后端/zookeeper/Zookeeper/image-20240520184926955.png",
    "后端/kafka/kafka/image-20240524120002017.png",
    "后端/kafka/kafka.md",
    "后端/zookeeper/Zookeeper.md",
    "后端/zookeeper/Zookeeper/image-20240520181453453.png",
    "杂记/啤酒江湖的醉意/image-20240527001134866.png",
    "杂记/啤酒江湖的醉意.md",
    "杂记/啤酒江湖的醉意/image-20240527001434239.png",
    "杂记/啤酒江湖的醉意/image-20240527001400733.png",
    "杂记/啤酒江湖的醉意",
    "杂记",
    "后端/kafka/kafka",
    "后端/kafka",
    "后端/后端1/zookeeper/未命名.md",
    "后端/kafka",
    "后端/kafka",
    "后端/后端1/第一篇.md",
    "后端/后端1/zookeeper/Zookeeper/image-20240520181432736.png",
    "后端/zookeeper/Zookeeper",
    "后端/zookeeper",
    "后端/后端2/dns.md",
    "后端/后端1/第一篇/Pasted image 20240518200523.png",
    "后端/后端1/第一篇/image-20240518200618525.png",
    "未命名.canvas",
    "前端/前端folder1/未命名.md",
    "后端/第一篇.md",
    "前端/folder2/未命名.md",
    "后端/未命名 2.md",
    "后端/未命名 1.md",
    "test4.md",
    "未命名.md",
    "test-img.md",
    "后端/test.md",
    "文章1.md",
    "未命名 2.md",
    "前端/未命名 6.md",
    "未命名 1.md",
    "前端/未命名 3.md",
    "Templates/Front-matter.md",
    "前端/未命名 5.md"
  ]
}